hellosetup/__init__.py
hellosetup/module1.py
hellosetup-0.0.2.dist-info/LICENSE.rst
hellosetup-0.0.2.dist-info/METADATA
hellosetup-0.0.2.dist-info/WHEEL
hellosetup-0.0.2.dist-info/top_level.txt
hellosetup-0.0.2.dist-info/RECORD
