Metadata-Version: 2.1
Name: hellosetup
Version: 0.0.2
Summary: A package created with a setuptools tutorial.  See article link for more details.
Home-page: https://codesolid.com/python-package-example-setuptools
License: BSD 3-Clause License
Project-URL: Source, https://github.com/CodeSolid/python-package-example-setuptools
Platform: UNKNOWN
License-File: LICENSE.rst
